{
  "visitreport": {
    "components": {
      "*": {
        "lead": [
          {
            "type": "lead",
            "duplicateCheckName": "lead",
            "label": {
              "en": "Lead",
              "de": "Interessent",
              "it": "Iniziative",
              "es": "Leads",
              "fr": "Intérêts potentiels"
            },
            "fields": {
              "leadid": {
                "id": "leadid",
                "type": "input",
                "label": {
                  "en": "id",
                  "de": ""
                },
                "properties": {
                  "hidden": true,
                  "identifier": true
                }
              },
              "assigneduserid": {
                "id": "assigneduserid",
                "type": "input",
                "label": {
                  "en": "Zugewiesen an",
                  "de": "Assigned to"
                },
                "properties": {
                  "hidden": true,
                  "identifier": true
                }
              },
              "personsalutation": {
                "id": "personsalutation",
                "type": "select",
                "label": {
                  "en": "Salutation",
                  "de": "Anrede",
                  "it": "Saluto",
                  "es": "Tratamiento",
                  "fr": "Civilité"
                },
                "properties": {}
              },
              "personfirstname": {
                "id": "personfirstname",
                "type": "input",
                "label": {
                  "en": "Firstname",
                  "de": "Vorname",
                  "it": "Nome",
                  "es": "Nombre",
                  "fr": "Prénom"
                },
                "properties": {
                  "required": true
                }
              },
              "personlastname": {
                "id": "personlastname",
                "type": "input",
                "label": {
                  "en": "Lastname",
                  "de": "Nachname",
                  "it": "Cognome",
                  "es": "Appellidos",
                  "fr": "Nom"
                },
                "properties": {
                  "required": true
                }
              },
              "companyname": {
                "id": "companyname",
                "type": "input",
                "label": {
                  "en": "Companyname",
                  "de": "Firmenname",
                  "it": "Società",
                  "es": "Compañia",
                  "fr": "Société"
                },
                "properties": {
                  "required": true
                }
              },
              "persontitle": {
                "id": "persontitle",
                "type": "input",
                "label": {
                  "en": "Title",
                  "de": "Titel",
                  "it": "Titolo",
                  "es": "Titulo académica",
                  "fr": "Titre académique"
                },
                "properties": {}
              },
              "personphonecountrycode": {
                "id": "personphonecountrycode",
                "type": "input",
                "label": {
                  "en": "Phone - Countrycode",
                  "de": "Telefon - Landesvorwahl",
                  "it": "Telefono - Codice paese",
                  "es": "Teléfono - Código de país",
                  "fr": "Téléphone - Code de pays"
                },
                "properties": {}
              },
              "personphoneareacode": {
                "id": "personphoneareacode",
                "type": "input",
                "label": {
                  "en": "Phone - AreaCode",
                  "de": "Telefon - Ortsvorwahl",
                  "it": "Telefono - Prefisso telefonico",
                  "es": "Teléfono - Código de área",
                  "fr": "Téléphone - Indicatif régional"
                },
                "properties": {}
              },
              "personphonenumber": {
                "id": "personphonenumber",
                "type": "input",
                "label": {
                  "en": "Phone",
                  "de": "Telefonnummer",
                  "it": "Numero di telefono",
                  "es": "Número de teléfono",
                  "fr": "Numéro de téléphone"
                },
                "properties": {}
              },
              "personfaxcountrycode": {
                "id": "personfaxcountrycode",
                "type": "input",
                "label": {
                  "en": "Fax - Countrycode",
                  "de": "Fax - Landesvorwahl",
                  "it": "Fax - Codice paese",
                  "es": "Fax - Código de país",
                  "fr": "Fax - Code de pays"
                },
                "properties": {}
              },
              "personfaxareacode": {
                "id": "personfaxareacode",
                "type": "input",
                "label": {
                  "en": "Fax - AreaCode",
                  "de": "Fax - Ortsvorwahl",
                  "it": "Fax - Prefisso telefonico",
                  "es": "Fax - Código de área",
                  "fr": "Fax - Indicatif régional"
                },
                "properties": {}
              },
              "personfaxnumber": {
                "id": "personfaxnumber",
                "type": "input",
                "label": {
                  "en": "Fax",
                  "de": "Faxnummer",
                  "it": "Numero di fax",
                  "es": "Número de fax",
                  "fr": "Numéro de télécopie"
                },
                "properties": {}
              },
              "personemail": {
                "id": "personemail",
                "type": "input",
                "label": {
                  "en": "E-mail",
                  "de": "E-Mail",
                  "it": "E-mail",
                  "es": "Correo electrónico",
                  "fr": "Adresse e-mail"
                },
                "properties": {}
              },
              "companywebsite": {
                "id": "companywebsite",
                "type": "input",
                "label": {
                  "en": "Website",
                  "de": "Website",
                  "it": "Sito Web",
                  "es": "Sito Web",
                  "fr": "Site Web"
                },
                "properties": {}
              },
              "companyaddress1": {
                "id": "companyaddress1",
                "type": "input",
                "label": {
                  "en": "Address 1",
                  "de": "Adresse 1",
                  "it": "Indirizzo 1",
                  "es": "Dirección 1",
                  "fr": "Adresse 1"
                },
                "properties": {}
              },
              "companypostcode": {
                "id": "companypostcode",
                "type": "input",
                "label": {
                  "en": "Zip",
                  "de": "PLZ",
                  "it": "Codice postale",
                  "es": "Código postal",
                  "fr": "Code postal"
                },
                "properties": {}
              },
              "companycity": {
                "id": "companycity",
                "type": "input",
                "label": {
                  "en": "City",
                  "de": "Stadt",
                  "it": "Città",
                  "es": "Cuidad",
                  "fr": "Ville"
                },
                "properties": {}
              },
              "companystate": {
                "id": "companystate",
                "type": "input",
                "label": {
                  "en": "State",
                  "de": "Bundesland",
                  "it": "Stato",
                  "es": "Estado o provincia",
                  "fr": "Région/Province"
                },
                "properties": {}
              },
              "companycountry": {
                "id": "companycountry",
                "type": "input",
                "label": {
                  "en": "Country",
                  "de": "Land",
                  "it": "Paese",
                  "es": "Pais",
                  "fr": "Pays"
                },
                "properties": {}
              },
              "source": {
                "id": "source",
                "type": "select",
                "label": {
                  "en": "Source",
                  "de": "Quelle",
                  "it": "Fonte",
                  "es": "Origen",
                  "fr": "Origine"
                },
                "properties": {}
              },
              "status": {
                "id": "status",
                "type": "select",
                "label": {
                  "en": "Status",
                  "de": "Status",
                  "it": "Stato",
                  "es": "Estado",
                  "fr": "Statut"
                },
                "properties": {}
              },
              "stage": {
                "id": "stage",
                "type": "select",
                "label": {
                  "en": "Stage",
                  "de": "Phase",
                  "it": "Fase",
                  "es": "Fase",
                  "fr": "Phase"
                },
                "properties": {}
              },
              "description": {
                "id": "description",
                "type": "input",
                "label": {
                  "en": "Description",
                  "de": "Beschreibung",
                  "it": "Descrizione",
                  "es": "Descripción",
                  "fr": "Description"
                },
                "properties": {}
              },
              "details": {
                "id": "details",
                "type": "textArea",
                "label": {
                  "en": "Details",
                  "de": "Details",
                  "it": "Dettagli",
                  "es": "Detalles",
                  "fr": "Détails"
                },
                "properties": {}
              }
            },
            "search": {
              "ids": [
                "personfirstname",
                "personlastname"
              ]
            },
            "mainTemplate": "{{ personfirstname || '' }} {{ personlastname || '' }}",
            "detailsTemplate": "{{ company }}"
          }
        ],
        "contact_account": [
          {
            "type": "contact",
            "duplicateCheckName": "contact",
            "label": {
              "en": "Person",
              "de": "Person",
              "it": "Persona",
              "es": "Persona",
              "fr": "Personne"
            },
            "fields": {
              "personid": {
                "id": "personid",
                "type": "input",
                "label": {
                  "en": "id",
                  "de": ""
                },
                "properties": {
                  "hidden": true,
                  "identifier": true
                }
              },
              "companyid": {
                "id": "companyid",
                "type": "input",
                "label": {
                  "en": "companyid",
                  "de": ""
                },
                "properties": {
                  "hidden": true
                }
              },
              "primaryaddressid": {
                "id": "primaryaddressid",
                "type": "input",
                "label": {
                  "en": "primaryaddressid",
                  "de": ""
                },
                "properties": {
                  "hidden": true,
                  "identifier": true
                }
              },
              "salutation": {
                "id": "salutation",
                "type": "select",
                "label": {
                  "en": "Salutation",
                  "de": "Anrede",
                  "it": "Saluto",
                  "es": "Tratamiento",
                  "fr": "Civilité"
                },
                "properties": {}
              },
              "title": {
                "id": "title",
                "type": "input",
                "label": {
                  "en": "Title",
                  "de": "Titel",
                  "it": "Titolo",
                  "es": "Titulo académica",
                  "fr": "Titre académique"
                },
                "properties": {}
              },
              "firstname": {
                "id": "firstname",
                "type": "input",
                "label": {
                  "en": "Firstname",
                  "de": "Vorname",
                  "it": "Nome",
                  "es": "Nombre",
                  "fr": "Prénom"
                },
                "properties": {
                  "required": true
                }
              },
              "lastname": {
                "id": "lastname",
                "type": "input",
                "label": {
                  "en": "LastName",
                  "de": "Nachname",
                  "it": "Cognome",
                  "es": "Appellidos",
                  "fr": "Nom"
                },
                "properties": {
                  "required": true
                }
              },
              "gender": {
                "id": "gender",
                "type": "select",
                "label": {
                  "en": "Gender",
                  "de": "Geschlecht",
                  "it": "Genere",
                  "es": "Género",
                  "fr": "Genre"
                },
                "properties": {}
              },
              "titlecode": {
                "id": "titlecode",
                "type": "select",
                "label": {
                  "en": "Position",
                  "de": "Funktion",
                  "it": "Posizione",
                  "es": "Posición",
                  "fr": "Titre du poste"
                },
                "properties": {}
              },
              "phone": {
                "id": "phone",
                "label": {
                  "en": "Phone",
                  "de": "Telefonnummer",
                  "it": "Telefono",
                  "es": "Teléfono",
                  "fr": "Téléphone"
                },
                "type": "sageSubPhone",
                "properties": {
                  "options": [
                    {
                      "id": "countrycode",
                      "label": {
                        "en": "Countrycode",
                        "de": "Ländervorwahl",
                        "it": "Codice paese",
                        "es": "Código de país",
                        "fr": "Code de pays"
                      },
                      "type": "input"
                    },
                    {
                      "id": "areacode",
                      "label": {
                        "en": "Areacode",
                        "de": "Ortsvorwahl",
                        "it": "Prefisso telefonico",
                        "es": "Código de área",
                        "fr": "Indicatif régional"
                      },
                      "type": "input"
                    },
                    {
                      "id": "number",
                      "label": {
                        "en": "Phone",
                        "de": "Telefonnummer",
                        "it": "Numero di telefono",
                        "es": "Número de teléfono",
                        "fr": "Numéro de téléphone"
                      },
                      "type": "input"
                    },
                    {
                      "id": "type",
                      "label": {
                        "en": "Type",
                        "de": "Typ",
                        "it": "Tipo",
                        "es": "Tipo",
                        "fr": "Tapez"
                      },
                      "type": "select",
                      "properties": {
                        "options": [
                          {
                            "label": {
                              "en": "Business",
                              "de": "Geschäftlich",
                              "es": "Trabajo",
                              "fr": "Travail",
                              "it": "Lavoro"
                            },
                            "value": "business"
                          },
                          {
                            "label": {
                              "en": "Fax",
                              "de": "Fax",
                              "es": "Fax",
                              "fr": "Télécopie",
                              "it": "Fax"
                            },
                            "value": "fax"
                          },
                          {
                            "label": {
                              "en": "Home",
                              "de": "Privat",
                              "es": "Privado",
                              "fr": "Privat",
                              "it": "Privato"
                            },
                            "value": "home"
                          },
                          {
                            "label": {
                              "en": "Mobile",
                              "de": "Mobil",
                              "es": "Móvil",
                              "fr": "Mobile",
                              "it": "Mobile"
                            },
                            "value": "mobile"
                          },
                          {
                            "label": {
                              "en": "Pager",
                              "de": "Pager",
                              "es": "Pager",
                              "fr": "Pager",
                              "it": "Pager"
                            },
                            "value": "pager"
                          }
                        ]
                      }
                    }
                  ]
                }
              },
              "email": {
                "id": "email",
                "label": {
                  "en": "E-mail",
                  "de": "E-Mail",
                  "es": "Correo electrónico",
                  "fr": "E-mail",
                  "it": "E-mail"
                },
                "type": "sageSubEmail",
                "properties": {
                  "options": [
                    {
                      "id": "emailaddress",
                      "label": {
                        "en": "Address",
                        "de": "Adresse",
                        "it": "Indirizzo",
                        "es": "Dirección",
                        "fr": "Adresse"
                      },
                      "type": "input"
                    },
                    {
                      "id": "type",
                      "label": {
                        "en": "Type",
                        "de": "Typ",
                        "it": "Tipo",
                        "es": "Tipo",
                        "fr": "Tapez"
                      },
                      "type": "select",
                      "properties": {
                        "options": [
                          {
                            "label": {
                              "en": "Business",
                              "de": "Geschäftlich",
                              "es": "Trabajo",
                              "fr": "Travail",
                              "it": "Lavoro"
                            },
                            "value": "business"
                          },
                          {
                            "label": {
                              "en": "Home",
                              "de": "Privat",
                              "es": "Privado",
                              "fr": "Privat",
                              "it": "Privato"
                            },
                            "value": "home"
                          }
                        ]
                      }
                    }
                  ]
                }
              },
              "website": {
                "id": "website",
                "type": "input",
                "label": {
                  "en": "Website",
                  "de": "Website",
                  "it": "Sito Web",
                  "es": "Sito Web",
                  "fr": "Site Web"
                },
                "properties": {}
              },
              "address": {
                "id": "address",
                "label": {
                  "en": "Primary address",
                  "de": "Hauptadresse",
                  "it": "Indirizzo principale",
                  "es": "Dirección principal",
                  "fr": "Adresse principale"
                },
                "type": "sageSubAddress",
                "properties": {
                  "options": [
                    {
                      "id": "address1",
                      "label": {
                        "en": "Address 1",
                        "de": "Adresse 1",
                        "it": "Indirizzo 1",
                        "es": "Dirección 1",
                        "fr": "Adresse 1"
                      },
                      "type": "input"
                    },
                    {
                      "id": "address2",
                      "label": {
                        "en": "Address 2",
                        "de": "Adresse 2",
                        "it": "Indirizzo 2",
                        "es": "Dirección 2",
                        "fr": "Adresse 2"
                      },
                      "type": "input"
                    },
                    {
                      "id": "address3",
                      "label": {
                        "en": "Address 3",
                        "de": "Adresse 3",
                        "it": "Indirizzo 3",
                        "es": "Dirección 3",
                        "fr": "Adresse 3"
                      },
                      "type": "input"
                    },
                    {
                      "id": "address4",
                      "label": {
                        "en": "Address 4",
                        "de": "Adresse 4",
                        "it": "Indirizzo 4",
                        "es": "Dirección 4",
                        "fr": "Adresse 4"
                      },
                      "type": "input"
                    },
                    {
                      "id": "address5",
                      "label": {
                        "en": "Address 5",
                        "de": "Adresse 5",
                        "it": "Indirizzo 5",
                        "es": "Dirección 5",
                        "fr": "Adresse 5"
                      },
                      "type": "input"
                    },
                    {
                      "id": "city",
                      "label": {
                        "en": "City",
                        "de": "Stadt",
                        "it": "Città",
                        "es": "Cuidad",
                        "fr": "Ville"
                      },
                      "type": "input"
                    },
                    {
                      "id": "postcode",
                      "label": {
                        "en": "Zip",
                        "de": "PLZ",
                        "it": "Codice postale",
                        "es": "Código postal",
                        "fr": "Code postal"
                      },
                      "type": "input"
                    },
                    {
                      "id": "state",
                      "label": {
                        "en": "State",
                        "de": "Bundesland",
                        "it": "Stato",
                        "es": "Estado o provincia",
                        "fr": "Région/Province"
                      },
                      "type": "input"
                    },
                    {
                      "id": "country",
                      "label": {
                        "en": "Country",
                        "de": "Land",
                        "it": "Paese",
                        "es": "Pais",
                        "fr": "Pays"
                      },
                      "type": "input"
                    },
                    {
                      "id": "type",
                      "label": {
                        "en": "Type",
                        "de": "Typ",
                        "it": "Tipo",
                        "es": "Tipo",
                        "fr": "Tapez"
                      },
                      "type": "multiselect",
                      "properties": {
                        "options": [
                          {
                            "label": {
                              "en": "Business",
                              "de": "Geschäftlich",
                              "es": "Trabajo",
                              "fr": "Travail",
                              "it": "Lavoro"
                            },
                            "value": "business"
                          },
                          {
                            "label": {
                              "en": "Billing",
                              "de": "Rechnungsadresse",
                              "it": "Indirizzo della fatturazione",
                              "es": "Dirección de correo",
                              "fr": "Adresse de facturation"
                            },
                            "value": "billing"
                          },
                          {
                            "label": {
                              "en": "Shipping",
                              "de": "Lieferadresse",
                              "it": "Indirizzo postale",
                              "es": "Dirección de envio",
                              "fr": "Adresse d'expédition"
                            },
                            "value": "shipping"
                          },
                          {
                            "label": {
                              "en": "home",
                              "de": "Privat",
                              "es": "Privado",
                              "fr": "Privat",
                              "it": "Privato"
                            },
                            "value": "home"
                          }
                        ]
                      }
                    }
                  ]
                }
              },
              "source": {
                "id": "source",
                "type": "select",
                "label": {
                  "en": "Source",
                  "de": "Quelle",
                  "it": "Fonte",
                  "es": "Origen",
                  "fr": "Origine"
                },
                "properties": {}
              },
              "status": {
                "id": "status",
                "type": "select",
                "label": {
                  "en": "Status",
                  "de": "Status",
                  "it": "Stato",
                  "es": "Estado",
                  "fr": "Statut"
                },
                "properties": {}
              }
            },
            "search": {
              "ids": [
                "firstname",
                "lastname"
              ]
            },
            "mainTemplate": "{{ firstname || '' }} {{ lastname || '' }}",
            "detailsTemplate": "{{ email.records[0].emailaddress }}"
          },
          {
            "type": "company",
            "duplicateCheckName": "account",
            "label": {
              "en": "Company",
              "de": "Firma",
              "it": "Società",
              "es": "Compañia",
              "fr": "Société"
            },
            "fields": {
              "companyid": {
                "id": "companyid",
                "type": "input",
                "label": {
                  "en": "id",
                  "de": ""
                },
                "properties": {
                  "hidden": true,
                  "identifier": true
                }
              },
              "primaryuserid": {
                "id": "primaryuserid",
                "type": "input",
                "label": {
                  "en": "primaryuserid",
                  "de": ""
                },
                "properties": {
                  "hidden": true,
                  "identifier": true
                }
              },
              "primaryaddressid": {
                "id": "primaryaddressid",
                "type": "input",
                "label": {
                  "en": "primaryaddressid",
                  "de": ""
                },
                "properties": {
                  "hidden": true,
                  "identifier": true
                }
              },
              "name": {
                "id": "name",
                "type": "input",
                "label": {
                  "en": "Name",
                  "de": "Name",
                  "it": "Nome",
                  "es": "Nombre",
                  "fr": "Nom"
                },
                "properties": {
                  "required": true
                }
              },
              "phone": {
                "id": "phone",
                "label": {
                  "en": "Phone",
                  "de": "Telefonnummer",
                  "it": "Telefono",
                  "es": "Teléfono",
                  "fr": "Téléphone"
                },
                "type": "sageSubPhone",
                "properties": {
                  "options": [
                    {
                      "id": "countrycode",
                      "label": {
                        "en": "Countrycode",
                        "de": "Ländervorwahl",
                        "it": "Codice paese",
                        "es": "Código de país",
                        "fr": "Code de pays"
                      },
                      "type": "input"
                    },
                    {
                      "id": "areacode",
                      "label": {
                        "en": "Areacode",
                        "de": "Ortsvorwahl",
                        "it": "Prefisso telefonico",
                        "es": "Código de área",
                        "fr": "Indicatif régional"
                      },
                      "type": "input"
                    },
                    {
                      "id": "number",
                      "label": {
                        "en": "Phone",
                        "de": "Telefonnummer",
                        "it": "Numero di telefono",
                        "es": "Número de teléfono",
                        "fr": "Numéro de téléphone"
                      },
                      "type": "input"
                    },
                    {
                      "id": "type",
                      "label": {
                        "en": "Type",
                        "de": "Typ",
                        "it": "Tipo",
                        "es": "Tipo",
                        "fr": "Tapez"
                      },
                      "type": "select",
                      "properties": {
                        "options": [
                          {
                            "label": {
                              "en": "Business",
                              "de": "Geschäftlich",
                              "es": "Trabajo",
                              "fr": "Travail",
                              "it": "Lavoro"
                            },
                            "value": "business"
                          },
                          {
                            "label": {
                              "en": "Fax",
                              "de": "Fax",
                              "es": "Fax",
                              "fr": "Télécopie",
                              "it": "Fax"
                            },
                            "value": "fax"
                          },
                          {
                            "label": {
                              "en": "Home",
                              "de": "Privat",
                              "es": "Privado",
                              "fr": "Privat",
                              "it": "Privato"
                            },
                            "value": "home"
                          },
                          {
                            "label": {
                              "en": "Mobile",
                              "de": "Mobil",
                              "es": "Móvil",
                              "fr": "Mobile",
                              "it": "Mobile"
                            },
                            "value": "mobile"
                          },
                          {
                            "label": {
                              "en": "Pager",
                              "de": "Pager",
                              "es": "Pager",
                              "fr": "Pager",
                              "it": "Pager"
                            },
                            "value": "pager"
                          }
                        ]
                      }
                    }
                  ]
                }
              },
              "email": {
                "id": "email",
                "label": {
                  "en": "E-mail",
                  "de": "E-Mail",
                  "es": "Correo electrónico",
                  "fr": "E-mail",
                  "it": "E-mail"
                },
                "type": "sageSubEmail",
                "properties": {
                  "options": [
                    {
                      "id": "emailaddress",
                      "label": {
                        "en": "Address",
                        "de": "Adresse",
                        "it": "Indirizzo",
                        "es": "Dirección",
                        "fr": "Adresse"
                      },
                      "type": "input"
                    },
                    {
                      "id": "type",
                      "label": {
                        "en": "Type",
                        "de": "Typ",
                        "it": "Tipo",
                        "es": "Tipo",
                        "fr": "Tapez"
                      },
                      "type": "select",
                      "properties": {
                        "options": [
                          {
                            "label": {
                              "en": "Business",
                              "de": "Geschäftlich",
                              "es": "Trabajo",
                              "fr": "Travail",
                              "it": "Lavoro"
                            },
                            "value": "business"
                          },
                          {
                            "label": {
                              "en": "Home",
                              "de": "Privat",
                              "es": "Privado",
                              "fr": "Privat",
                              "it": "Privato"
                            },
                            "value": "home"
                          }
                        ]
                      }
                    }
                  ]
                }
              },
              "website": {
                "id": "website",
                "type": "input",
                "label": {
                  "en": "Website",
                  "de": "Website",
                  "it": "Sito Web",
                  "es": "Sito Web",
                  "fr": "Site Web"
                },
                "properties": {}
              },
              "address": {
                "id": "address",
                "label": {
                  "en": "Primary address",
                  "de": "Hauptadresse",
                  "it": "Indirizzo principale",
                  "es": "Dirección principal",
                  "fr": "Adresse principale"
                },
                "type": "sageSubAddress",
                "properties": {
                  "options": [
                    {
                      "id": "address1",
                      "label": {
                        "en": "Address 1",
                        "de": "Adresse 1",
                        "it": "Indirizzo 1",
                        "es": "Dirección 1",
                        "fr": "Adresse 1"
                      },
                      "type": "input"
                    },
                    {
                      "id": "address2",
                      "label": {
                        "en": "Address 2",
                        "de": "Adresse 2",
                        "it": "Indirizzo 2",
                        "es": "Dirección 2",
                        "fr": "Adresse 2"
                      },
                      "type": "input"
                    },
                    {
                      "id": "address3",
                      "label": {
                        "en": "Address 3",
                        "de": "Adresse 3",
                        "it": "Indirizzo 3",
                        "es": "Dirección 3",
                        "fr": "Adresse 3"
                      },
                      "type": "input"
                    },
                    {
                      "id": "address4",
                      "label": {
                        "en": "Address 4",
                        "de": "Adresse 4",
                        "it": "Indirizzo 4",
                        "es": "Dirección 4",
                        "fr": "Adresse 4"
                      },
                      "type": "input"
                    },
                    {
                      "id": "address5",
                      "label": {
                        "en": "Address 5",
                        "de": "Adresse 5",
                        "it": "Indirizzo 5",
                        "es": "Dirección 5",
                        "fr": "Adresse 5"
                      },
                      "type": "input"
                    },
                    {
                      "id": "city",
                      "label": {
                        "en": "City",
                        "de": "Stadt",
                        "it": "Città",
                        "es": "Cuidad",
                        "fr": "Ville"
                      },
                      "type": "input"
                    },
                    {
                      "id": "postcode",
                      "label": {
                        "en": "Zip",
                        "de": "PLZ",
                        "it": "Codice postale",
                        "es": "Código postal",
                        "fr": "Code postal"
                      },
                      "type": "input"
                    },
                    {
                      "id": "state",
                      "label": {
                        "en": "State",
                        "de": "Bundesland",
                        "it": "Stato",
                        "es": "Estado o provincia",
                        "fr": "Région/Province"
                      },
                      "type": "input"
                    },
                    {
                      "id": "country",
                      "label": {
                        "en": "Country",
                        "de": "Land",
                        "it": "Paese",
                        "es": "Pais",
                        "fr": "Pays"
                      },
                      "type": "input"
                    },
                    {
                      "id": "type",
                      "label": {
                        "en": "Type",
                        "de": "Typ",
                        "it": "Tipo",
                        "es": "Tipo",
                        "fr": "Tapez"
                      },
                      "type": "multiselect",
                      "properties": {
                        "options": [
                          {
                            "label": {
                              "en": "Business",
                              "de": "Geschäftlich",
                              "es": "Trabajo",
                              "fr": "Travail",
                              "it": "Lavoro"
                            },
                            "value": "business"
                          },
                          {
                            "label": {
                              "en": "Billing",
                              "de": "Rechnungsadresse",
                              "it": "Indirizzo della fatturazione",
                              "es": "Dirección de correo",
                              "fr": "Adresse de facturation"
                            },
                            "value": "billing"
                          },
                          {
                            "label": {
                              "en": "Shipping",
                              "de": "Lieferadresse",
                              "it": "Indirizzo postale",
                              "es": "Dirección de envio",
                              "fr": "Adresse d'expédition"
                            },
                            "value": "shipping"
                          },
                          {
                            "label": {
                              "en": "home",
                              "de": "Privat",
                              "es": "Privado",
                              "fr": "Privat",
                              "it": "Privato"
                            },
                            "value": "home"
                          }
                        ]
                      }
                    }
                  ]
                }
              },
              "status": {
                "id": "status",
                "type": "input",
                "label": {
                  "en": "Status",
                  "de": "Status",
                  "it": "Stato",
                  "es": "Estado",
                  "fr": "Statut"
                },
                "properties": {}
              }
            },
            "search": {
              "ids": [
                "name"
              ]
            },
            "mainTemplate": "{{ name }}",
            "detailsTemplate": "{{ address.records[0].postcode || '' }} {{ address.records[0].city || '' }}"
          }
        ]
      }
    }
  }
}